django_mongoengine/__init__.py
django_mongoengine/apps.py
django_mongoengine/document.py
django_mongoengine/fields/__init__.py
django_mongoengine/fields/djangoflavor.py
django_mongoengine/forms/__init__.py
django_mongoengine/forms/document_options.py
django_mongoengine/forms/documents.py
django_mongoengine/forms/fields.py
django_mongoengine/forms/utils.py
django_mongoengine/forms/widgets.py
django_mongoengine/mongo_admin/__init__.py
django_mongoengine/mongo_admin/actions.py
django_mongoengine/mongo_admin/apps.py
django_mongoengine/mongo_admin/decorators.py
django_mongoengine/mongo_admin/helpers.py
django_mongoengine/mongo_admin/management/__init__.py
django_mongoengine/mongo_admin/management/commands/__init__.py
django_mongoengine/mongo_admin/management/commands/createmongodbsuperuser.py
django_mongoengine/mongo_admin/options.py
django_mongoengine/mongo_admin/sites.py
django_mongoengine/mongo_admin/static/dict.js
django_mongoengine/mongo_admin/static/helper.js
django_mongoengine/mongo_admin/static/jquery-1.8.0.min.js
django_mongoengine/mongo_admin/templates/admin/change_document_list.html
django_mongoengine/mongo_admin/templates/mongo_admin/index.html
django_mongoengine/mongo_admin/templatetags/__init__.py
django_mongoengine/mongo_admin/templatetags/documenttags.py
django_mongoengine/mongo_admin/templatetags/mongoadmintags.py
django_mongoengine/mongo_admin/util.py
django_mongoengine/mongo_admin/validation.py
django_mongoengine/mongo_admin/views.py
django_mongoengine/mongo_auth/__init__.py
django_mongoengine/mongo_auth/admin.py
django_mongoengine/mongo_auth/backends.py
django_mongoengine/mongo_auth/managers.py
django_mongoengine/mongo_auth/models.py
django_mongoengine/paginator.py
django_mongoengine/queryset.py
django_mongoengine/sessions.py
django_mongoengine/utils/__init__.py
django_mongoengine/utils/monkey.py
django_mongoengine/utils/patches.py
django_mongoengine/utils/wrappers.py
django_mongoengine/views/__init__.py
django_mongoengine/views/detail.py
django_mongoengine-0.4.1.dist-info/LICENSE
django_mongoengine-0.4.1.dist-info/WHEEL
django_mongoengine-0.4.1.dist-info/METADATA
django_mongoengine-0.4.1.dist-info/RECORD
