Metadata-Version: 2.1
Name: django-mongoengine
Version: 0.4.1
Summary: Django support for MongoDB via MongoEngine
Author: Ross Lawley
Author-email: ross.lawley@gmail.com
Requires-Python: >=2.7
Classifier: Programming Language :: Python :: 2
Classifier: Programming Language :: Python :: 2.7
Classifier: Programming Language :: Python :: 3
Classifier: Programming Language :: Python :: 3.4
Classifier: Programming Language :: Python :: 3.5
Classifier: Programming Language :: Python :: 3.6
Classifier: Programming Language :: Python :: 3.7
Classifier: Programming Language :: Python :: 3.8
Requires-Dist: django (>1.11)
Requires-Dist: mongoengine (>=0.14)
